dts_utils/__init__.py
dts_utils/__version__.py
dts_utils/builder.py
dts_utils/dts.py
dts_utils/dump.py
dts_utils/exceptions.py
dts_utils/filters.py
dts_utils/node.py
dts_utils/property.py
dts_utils/py.typed
dts_utils/tests.py
dts_utils-0.4.0.dist-info/licenses/LICENSE
dts_utils-0.4.0.dist-info/METADATA
dts_utils-0.4.0.dist-info/WHEEL
dts_utils-0.4.0.dist-info/entry_points.txt
dts_utils-0.4.0.dist-info/top_level.txt
dts_utils-0.4.0.dist-info/RECORD
