Metadata-Version: 2.4
Name: dts-utils
Version: 0.4.0
Summary: DTS utility python package
Author-email: Ledger SAS <firmware@ledger.fr>
License: 
Project-URL: Homepage, https://github.com/camelot-os
Project-URL: Repository, https://github.com/camelot-os/python-dts-utils
Project-URL: Issues, https://github.com/camelot-os/python-dts-utils/issues
Classifier: Development Status :: 4 - Beta
Classifier: Intended Audience :: Developers
Classifier: Topic :: Software Development :: Build Tools
Classifier: License :: OSI Approved :: Apache Software License
Classifier: Programming Language :: Python :: 3
Classifier: Programming Language :: Python :: 3 :: Only
Classifier: Programming Language :: Python :: 3.10
Classifier: Programming Language :: Python :: 3.11
Classifier: Programming Language :: Python :: 3.12
Requires-Python: >=3.10
License-File: LICENSE
Requires-Dist: devicetree>=0.0.2
Requires-Dist: Jinja2>3
Requires-Dist: rich
Provides-Extra: devel
Requires-Dist: flake8<8.0,>=7.0; extra == "devel"
Requires-Dist: mypy>=1.8.0; extra == "devel"
Requires-Dist: pytest>=4.6; extra == "devel"
Requires-Dist: pytest-cov>=5.0.0; extra == "devel"
Requires-Dist: black<25.0,>=24.2; extra == "devel"
Requires-Dist: pydoclint; extra == "devel"
Requires-Dist: flake8-docstrings; extra == "devel"
Provides-Extra: doc
Requires-Dist: Sphinx>=7.2.0; extra == "doc"
Requires-Dist: sphinx-rtd-theme>=2.0.0; extra == "doc"
Requires-Dist: sphinx-simplepdf>=1.6.0; extra == "doc"
Requires-Dist: sphinx-autoapi; extra == "doc"
Dynamic: license-file
